particleloader/__init__.py
particleloader/_version.py
particleloader/loader.py
particleloader/utils.py
particleloader/Datasets/Dataset.py
particleloader/Datasets/SPECTER_ee_dijets.py
particleloader/Datasets/SPECTER_qcd_jets.py
particleloader/Datasets/SPECTER_top_jets.py
particleloader/Datasets/__init__.py
particleloader/Datasets/qg_jets.py
particleloader/Datasets/topqcd_jets.py
particleloader-0.0.7.post4.data/data/LICENSE
particleloader-0.0.7.post4.data/data/README.md
particleloader-0.0.7.post4.data/data/pyproject.toml
particleloader-0.0.7.post4.dist-info/LICENSE
particleloader-0.0.7.post4.dist-info/METADATA
particleloader-0.0.7.post4.dist-info/WHEEL
particleloader-0.0.7.post4.dist-info/top_level.txt
particleloader-0.0.7.post4.dist-info/RECORD
