Metadata-Version: 2.1
Name: particleloader
Version: 0.0.7.post4
Summary: Code for downloading Particle Physics datasets
Home-page: https://github.com/rikab/ParticleLoader
Author: Rikab Gambhir
Author-email: Rikab Gambhir <rikab@mit.edu>
License: MIT
Project-URL: Documentation, https://github.com/rikab/ParticleLoader
Project-URL: Homepage, https://github.com/rikab/ParticleLoader
Project-URL: Issue Tracker, https://github.com/rikab/ParticleLoader/issues
Project-URL: Releases, https://github.com/rikab/ParticleLoader/releases
Project-URL: Source Code, https://github.com/rikab/ParticleLoader
Keywords: top tagging,jet physics,machine learning
Classifier: Development Status :: 3 - Alpha
Classifier: Intended Audience :: Science/Research
Classifier: License :: OSI Approved :: MIT License
Classifier: Programming Language :: Python :: 3
Classifier: Programming Language :: Python :: 3 :: Only
Classifier: Programming Language :: Python :: 3.7
Classifier: Programming Language :: Python :: 3.8
Classifier: Programming Language :: Python :: 3.9
Classifier: Programming Language :: Python :: 3.10
Classifier: Programming Language :: Python :: Implementation :: CPython
Classifier: Topic :: Scientific/Engineering
Classifier: Topic :: Scientific/Engineering :: Physics
Requires-Python: >=3.7
License-File: LICENSE
Requires-Dist: pandas
Requires-Dist: tqdm
Requires-Dist: matplotlib>=3.5.0
Requires-Dist: numpy
